copulax/__init__.py
copulax/special.py
copulax/_src/README.md
copulax/_src/__init__.py
copulax/_src/_distributions.py
copulax/_src/_utils.py
copulax/_src/optimize.py
copulax/_src/special.py
copulax/_src/typing.py
copulax/_src/copulas/_distributions.py
copulax/_src/multivariate/_shape.py
copulax/_src/multivariate/_utils.py
copulax/_src/multivariate/mvt_gh.py
copulax/_src/multivariate/mvt_normal.py
copulax/_src/multivariate/mvt_skewed_t.py
copulax/_src/multivariate/mvt_student_t.py
copulax/_src/univariate/__init__.py
copulax/_src/univariate/_approx.py
copulax/_src/univariate/_cdf.py
copulax/_src/univariate/_mean_variance.py
copulax/_src/univariate/_metrics.py
copulax/_src/univariate/_ppf.py
copulax/_src/univariate/_rvs.py
copulax/_src/univariate/_utils.py
copulax/_src/univariate/gamma.py
copulax/_src/univariate/gh.py
copulax/_src/univariate/gig.py
copulax/_src/univariate/ig.py
copulax/_src/univariate/lognormal.py
copulax/_src/univariate/normal.py
copulax/_src/univariate/skewed_t.py
copulax/_src/univariate/student_t.py
copulax/_src/univariate/uniform.py
copulax/_src/univariate/univariate_fitter.py
copulax/copulas/README.md
copulax/copulas/__init__.py
copulax/multivariate/README.md
copulax/multivariate/__init__.py
copulax/tests/helpers.py
copulax/tests/test_special.py
copulax/tests/test_utils.py
copulax/tests/copulas/conftest.py
copulax/tests/copulas/test_copulas.py
copulax/tests/multivariate/conftest.py
copulax/tests/multivariate/test_multivariate.py
copulax/tests/multivariate/test_shape.py
copulax/tests/univariate/conftest.py
copulax/tests/univariate/test_univariate.py
copulax/tests/univariate/test_univariate_fitter.py
copulax/univariate/README.md
copulax/univariate/__init__.py
copulax/univariate/distributions.py
copulax-1.0.1.dist-info/licenses/LICENSE.txt
copulax-1.0.1.dist-info/METADATA
copulax-1.0.1.dist-info/WHEEL
copulax-1.0.1.dist-info/top_level.txt
copulax-1.0.1.dist-info/RECORD
