Metadata-Version: 2.4
Name: copulax
Version: 1.0.1
Summary: Copula, multivariate and univariate distribution fitting using JAX in python.
Author-email: Tyler Mitchell <tylerfmitchell1999@gmail.com>
Maintainer-email: Tyler Mitchell <tylerfmitchell1999@gmail.com>
License: MIT License
Project-URL: Homepage, https://github.com/tfm000/copulax
Project-URL: Bug Reports, https://github.com/tfm000/copulax/issues
Project-URL: Source, https://github.com/tfm000/copulax
Keywords: Sklar,Copula,Copulas,Copulae,Probability,Distribution,Univariate,Bivariate,Multivariate,Joint,CDF,PDF,Modeling,Quantitative,Fitting,SciPy,Statistics,Mathematics,Science,Scientific,Finance,Risk,VaR,Machine Learning,Variables,JAX
Classifier: Development Status :: 3 - Alpha
Classifier: Intended Audience :: Science/Research
Classifier: Intended Audience :: Financial and Insurance Industry
Classifier: Intended Audience :: Developers
Classifier: Intended Audience :: Education
Classifier: Topic :: Software Development :: Build Tools
Classifier: License :: OSI Approved :: MIT License
Classifier: Programming Language :: Python :: 3.10
Classifier: Programming Language :: Python :: 3.11
Classifier: Programming Language :: Python :: 3.12
Classifier: Topic :: Scientific/Engineering
Classifier: Topic :: Scientific/Engineering :: Mathematics
Classifier: Topic :: Scientific/Engineering :: Artificial Intelligence
Classifier: Topic :: Software Development
Classifier: Topic :: Software Development :: Libraries
Classifier: Topic :: Software Development :: Libraries :: Python Modules
Requires-Python: <3.13,>=3.10
License-File: LICENSE.txt
Requires-Dist: jax>=0.4.31
Requires-Dist: jaxopt>=0.8.3
Requires-Dist: quadax>=0.2.2
Requires-Dist: requests>=2.32.3
Requires-Dist: tensorflow-probability>=0.25.0
Requires-Dist: interpax>=0.3.7
Requires-Dist: matplotlib>=3.9.2
Provides-Extra: dev
Requires-Dist: pytest==8.3.4; extra == "dev"
Requires-Dist: pytest-cov==6.0.0; extra == "dev"
Requires-Dist: build; extra == "dev"
Requires-Dist: twine; extra == "dev"
Dynamic: license-file
